[
    { "symbol": "AAPL", "name": "Apple Inc." },
    { "symbol": "MSFT", "name": "Microsoft Corporation" },
    { "symbol": "GOOGL", "name": "Alphabet Inc." },
    { "symbol": "AMZN", "name": "Amazon.com Inc." },
    { "symbol": "TSLA", "name": "Tesla Inc." },
    { "symbol": "NVDA", "name": "NVIDIA Corporation" },
    { "symbol": "PYPL", "name": "PayPal Holdings Inc." },
    { "symbol": "ADBE", "name": "Adobe Inc." },
    { "symbol": "CRM", "name": "Salesforce.com Inc." },
    { "symbol": "INTC", "name": "Intel Corporation" },
    { "symbol": "NFLX", "name": "Netflix Inc." },
    { "symbol": "CMCSA", "name": "Comcast Corporation" },
    { "symbol": "CSCO", "name": "Cisco Systems Inc." },
    { "symbol": "AVGO", "name": "Broadcom Inc." },
    { "symbol": "PEP", "name": "PepsiCo Inc." },
    { "symbol": "TMUS", "name": "T-Mobile US Inc." },
    { "symbol": "QCOM", "name": "Qualcomm Incorporated" },
    { "symbol": "COST", "name": "Costco Wholesale Corporation" },
    { "symbol": "AMGN", "name": "Amgen Inc." },
    { "symbol": "TXN", "name": "Texas Instruments Incorporated" },
    { "symbol": "SBUX", "name": "Starbucks Corporation" },
    { "symbol": "CHTR", "name": "Charter Communications Inc." },
    { "symbol": "INTU", "name": "Intuit Inc." },
    { "symbol": "AMD", "name": "Advanced Micro Devices Inc." },
    { "symbol": "ISRG", "name": "Intuitive Surgical Inc." },
    { "symbol": "ADP", "name": "Automatic Data Processing Inc." },
    { "symbol": "MU", "name": "Micron Technology Inc." },
    { "symbol": "MRK", "name": "Merck & Co. Inc." },
    { "symbol": "GILD", "name": "Gilead Sciences Inc." },
    { "symbol": "MDLZ", "name": "Mondelez International Inc." },
    { "symbol": "BIIB", "name": "Biogen Inc." },
    { "symbol": "ATVI", "name": "Activision Blizzard Inc." },
    { "symbol": "BKNG", "name": "Booking Holdings Inc." },
    { "symbol": "T", "name": "AT&T Inc." },
    { "symbol": "TMO", "name": "Thermo Fisher Scientific Inc." },
    { "symbol": "LRCX", "name": "Lam Research Corporation" },
    { "symbol": "NOW", "name": "ServiceNow Inc." },
    { "symbol": "VRTX", "name": "Vertex Pharmaceuticals Incorporated" },
    { "symbol": "CVS", "name": "CVS Health Corporation" },
    { "symbol": "ZM", "name": "Zoom Video Communications Inc." },
    { "symbol": "ABNB", "name": "Airbnb Inc." },
    { "symbol": "DHR", "name": "Danaher Corporation" },
    { "symbol": "SYK", "name": "Stryker Corporation" },
    { "symbol": "FIS", "name": "Fidelity National Information Services Inc." },
    { "symbol": "SPGI", "name": "S&P Global Inc." },
    { "symbol": "ROST", "name": "Ross Stores Inc." },
    { "symbol": "ADI", "name": "Analog Devices Inc." },
    { "symbol": "MCD", "name": "McDonald's Corporation" },
    { "symbol": "MO", "name": "Altria Group Inc." },
    { "symbol": "PLD", "name": "Prologis Inc." },
    { "symbol": "LOW", "name": "Lowe's Companies Inc." },
    { "symbol": "CAT", "name": "Caterpillar Inc." },
    { "symbol": "MS", "name": "Morgan Stanley" },
    { "symbol": "SPG", "name": "Simon Property Group Inc." },
    { "symbol": "BDX", "name": "Becton Dickinson and Company" },
    { "symbol": "MDT", "name": "Medtronic plc" },
    { "symbol": "D", "name": "Dominion Energy Inc." },
    { "symbol": "BK", "name": "The Bank of New York Mellon Corporation" },
    { "symbol": "GPN", "name": "Global Payments Inc." },
    { "symbol": "AON", "name": "Aon plc" },
    { "symbol": "AMAT", "name": "Applied Materials Inc." },
    { "symbol": "MUFG", "name": "Mitsubishi UFJ Financial Group Inc." },
    { "symbol": "KHC", "name": "Kraft Heinz Company" },
    { "symbol": "FDX", "name": "FedEx Corporation" },
    { "symbol": "WMB", "name": "Williams Companies Inc." },
    { "symbol": "NOC", "name": "Northrop Grumman Corporation" },
    { "symbol": "PLTR", "name": "Palantir Technologies Inc." },
    { "symbol": "CI", "name": "Cigna Corporation" },
    { "symbol": "MET", "name": "MetLife Inc." },
    { "symbol": "WFC", "name": "Wells Fargo & Company" },
    { "symbol": "ORCL", "name": "Oracle Corporation" },
    { "symbol": "RACE", "name": "Ferrari N.V." },
    { "symbol": "EBAY", "name": "eBay Inc." },
    { "symbol": "VMW", "name": "VMware Inc." },
    { "symbol": "VMC", "name": "Vulcan Materials Company" },
    { "symbol": "XOM", "name": "Exxon Mobil Corporation" },
    { "symbol": "OXY", "name": "Occidental Petroleum Corporation" },
    { "symbol": "COP", "name": "ConocoPhillips" },
    { "symbol": "EOG", "name": "EOG Resources Inc." },
    { "symbol": "MRO", "name": "Marathon Oil Corporation" },
    { "symbol": "DVN", "name": "Devon Energy Corporation" },
    { "symbol": "APA", "name": "APA Corporation" },
    { "symbol": "HAL", "name": "Halliburton Company" },
    { "symbol": "CCL", "name": "Carnival Corporation & plc" },
    { "symbol": "AAL", "name": "American Airlines Group Inc." },
    { "symbol": "EXPE", "name": "Expedia Group Inc." },
    { "symbol": "MAR", "name": "Marriott International Inc." },
    { "symbol": "HLT", "name": "Hilton Worldwide Holdings Inc." },
    { "symbol": "LVS", "name": "Las Vegas Sands Corp." },
    { "symbol": "NCLH", "name": "Norwegian Cruise Line Holdings Ltd." },
    { "symbol": "RCL", "name": "Royal Caribbean Group" },
    { "symbol": "MGM", "name": "MGM Resorts International" },
    { "symbol": "HAS", "name": "Hasbro Inc." },
    { "symbol": "MAT", "name": "Mattel Inc." },
    { "symbol": "LW", "name": "Lamb Weston Holdings Inc." },
    { "symbol": "CLX", "name": "The Clorox Company" },
    { "symbol": "HSY", "name": "The Hershey Company" },
    { "symbol": "GIS", "name": "General Mills Inc." },
    { "symbol": "MKC", "name": "McCormick & Company Incorporated" },
    { "symbol": "KMB", "name": "Kimberly-Clark Corporation" },
    { "symbol": "SJM", "name": "The J. M. Smucker Company" },
    { "symbol": "DEO", "name": "Diageo plc" },
    { "symbol": "BF-B", "name": "Brown-Forman Corporation" },
    { "symbol": "BTI", "name": "British American Tobacco p.l.c." },
    { "symbol": "MO", "name": "Altria Group Inc." },
    { "symbol": "PM", "name": "Philip Morris International Inc." },
    { "symbol": "PFE", "name": "Pfizer Inc." },
    { "symbol": "LLY", "name": "Eli Lilly and Company" },
    { "symbol": "GSK", "name": "GlaxoSmithKline plc" },
    { "symbol": "NVS", "name": "Novartis AG" },
    { "symbol": "SNY", "name": "Sanofi" },
    { "symbol": "ABBV", "name": "AbbVie Inc." },
    { "symbol": "BMY", "name": "Bristol-Myers Squibb Company" },
    { "symbol": "TMO", "name": "Thermo Fisher Scientific Inc." },
    { "symbol": "DHR", "name": "Danaher Corporation" },
    { "symbol": "MMM", "name": "3M Company" },
    { "symbol": "GE", "name": "General Electric Company" },
    { "symbol": "CAT", "name": "Caterpillar Inc." },
    { "symbol": "BA", "name": "The Boeing Company" },
    { "symbol": "LMT", "name": "Lockheed Martin Corporation" },
    { "symbol": "GD", "name": "General Dynamics Corporation" },
    { "symbol": "RTX", "name": "Raytheon Technologies Corporation" },
    { "symbol": "NOC", "name": "Northrop Grumman Corporation" },
    { "symbol": "HON", "name": "Honeywell International Inc." },
    { "symbol": "UPS", "name": "United Parcel Service Inc." },
    { "symbol": "FDX", "name": "FedEx Corporation" },
    { "symbol": "CMI", "name": "Cummins Inc." },
    { "symbol": "WM", "name": "Waste Management Inc." },
    { "symbol": "RSG", "name": "Republic Services Inc." },
    { "symbol": "DUK", "name": "Duke Energy Corporation" },
    { "symbol": "SO", "name": "The Southern Company" },
    { "symbol": "NEE", "name": "NextEra Energy Inc." },
    { "symbol": "D", "name": "Dominion Energy Inc." },
    { "symbol": "EXC", "name": "Exelon Corporation" },
    { "symbol": "AEP", "name": "American Electric Power Company Inc." },
    { "symbol": "XEL", "name": "Xcel Energy Inc." },
    { "symbol": "ETR", "name": "Entergy Corporation" },
    { "symbol": "CMS", "name": "CMS Energy Corporation" },
    { "symbol": "PEG", "name": "Public Service Enterprise Group Incorporated" },
    { "symbol": "PCG", "name": "PG&E Corporation" },
    { "symbol": "ED", "name": "Consolidated Edison Inc." },
    { "symbol": "AWK", "name": "American Water Works Company Inc." },
    { "symbol": "CNP", "name": "CenterPoint Energy Inc." },
    { "symbol": "WEC", "name": "WEC Energy Group Inc." },
    { "symbol": "PNW", "name": "Pinnacle West Capital Corporation" },
    { "symbol": "FE", "name": "FirstEnergy Corp." },
    { "symbol": "NI", "name": "NiSource Inc." },
    { "symbol": "ES", "name": "Eversource Energy" },
    { "symbol": "DTE", "name": "DTE Energy Company" },
    { "symbol": "AES", "name": "The AES Corporation" },
    { "symbol": "NRG", "name": "NRG Energy Inc." },
    { "symbol": "EXC", "name": "Exelon Corporation" },
    { "symbol": "FE", "name": "FirstEnergy Corp." },
    { "symbol": "XEL", "name": "Xcel Energy Inc." },
    { "symbol": "AEP", "name": "American Electric Power Company Inc." },
    { "symbol": "D", "name": "Dominion Energy Inc." },
    { "symbol": "DUK", "name": "Duke Energy Corporation" },
    { "symbol": "SO", "name": "The Southern Company" },
    { "symbol": "NEE", "name": "NextEra Energy Inc." },
    { "symbol": "SRE", "name": "Sempra Energy" },
    { "symbol": "EIX", "name": "Edison International" },
    { "symbol": "PCG", "name": "PG&E Corporation" },
    { "symbol": "WEC", "name": "WEC Energy Group Inc." },
    { "symbol": "AWK", "name": "American Water Works Company Inc." },
    { "symbol": "ED", "name": "Consolidated Edison Inc." },
    { "symbol": "CMS", "name": "CMS Energy Corporation" },
    { "symbol": "ETR", "name": "Entergy Corporation" },
    { "symbol": "PNW", "name": "Pinnacle West Capital Corporation" },
    { "symbol": "PEG", "name": "Public Service Enterprise Group Incorporated" },
    { "symbol": "CNP", "name": "CenterPoint Energy Inc." },
    { "symbol": "NEM", "name": "Newmont Corporation" },
    { "symbol": "GOLD", "name": "Barrick Gold Corporation" },
    { "symbol": "FNV", "name": "Franco-Nevada Corporation" },
    { "symbol": "WPM", "name": "Wheaton Precious Metals Corp." },
    { "symbol": "AEM", "name": "Agnico Eagle Mines Limited" },
    { "symbol": "RGLD", "name": "Royal Gold Inc." },
    { "symbol": "SAND", "name": "Sandstorm Gold Ltd." },
    { "symbol": "AG", "name": "First Majestic Silver Corp." },
    { "symbol": "PAAS", "name": "Pan American Silver Corp." },
    { "symbol": "BTG", "name": "B2Gold Corp." },
    { "symbol": "GFI", "name": "Gold Fields Limited" },
    { "symbol": "NGD", "name": "New Gold Inc." },
    { "symbol": "AGI", "name": "Alamos Gold Inc." },
    { "symbol": "HMY", "name": "Harmony Gold Mining Company Limited" },
    { "symbol": "ELEMF", "name": "Elemental Royalties Corp." },
    { "symbol": "EXXRF", "name": "Exore Resources Ltd." },
    { "symbol": "FSM", "name": "Fortuna Silver Mines Inc." },
    { "symbol": "HL", "name": "Hecla Mining Company" },
    { "symbol": "IAG", "name": "IAMGOLD Corporation" },
    { "symbol": "KGC", "name": "Kinross Gold Corporation" }
]
